[{"domain":"one.beauty","status":"available","attractiveness":132,"demand":44,"length":3,"created":"","expires":"","registrar":null,"sectors":"Business,General,Media,Technology"},{"domain":"second.beauty","status":"available","attractiveness":120,"demand":23,"length":6,"created":"","expires":"","registrar":null,"sectors":"General,Mathematics"},{"domain":"flat.beauty","status":"available","attractiveness":116,"demand":24,"length":4,"created":"","expires":"","registrar":null,"sectors":"Construction,Real Estate"},{"domain":"tenth.beauty","status":"available","attractiveness":116,"demand":7,"length":5,"created":"","expires":"","registrar":null,"sectors":"Mathematics"},{"domain":"zero.beauty","status":"resell","attractiveness":112,"demand":49,"length":4,"created":"2024-10-25T13:46:05.000Z","expires":"2025-10-25T23:59:59.000Z","registrar":"Xiamen ChinaSource Internet Service Co., Ltd","sectors":"Mathematics"},{"domain":"nought.beauty","status":"available","attractiveness":92,"demand":4,"length":6,"created":"","expires":"","registrar":null,"sectors":"Mathematics"},{"domain":"twentieth.beauty","status":"available","attractiveness":92,"demand":3,"length":9,"created":"","expires":"","registrar":null,"sectors":"Mathematics"},{"domain":"leash.beauty","status":"available","attractiveness":90,"demand":7,"length":5,"created":"","expires":"","registrar":null,"sectors":"General,Health and Fitness,Retail"},{"domain":"hundred.beauty","status":"available","attractiveness":88,"demand":14,"length":7,"created":"","expires":"","registrar":null,"sectors":"Mathematics"},{"domain":"fifteen.beauty","status":"available","attractiveness":88,"demand":13,"length":7,"created":"","expires":"","registrar":null,"sectors":"Mathematics"},{"domain":"eleven.beauty","status":"available","attractiveness":88,"demand":33,"length":6,"created":"","expires":"","registrar":null,"sectors":"Mathematics"},{"domain":"ace.beauty","status":"available","attractiveness":88,"demand":34,"length":3,"created":"","expires":"","registrar":null,"sectors":"Sports"},{"domain":"three.beauty","status":"available","attractiveness":88,"demand":24,"length":5,"created":"","expires":"","registrar":null,"sectors":"Mathematics"},{"domain":"twelve.beauty","status":"available","attractiveness":88,"demand":18,"length":6,"created":"","expires":"","registrar":null,"sectors":"General,Mathematics"},{"domain":"ten.beauty","status":"available","attractiveness":88,"demand":28,"length":3,"created":"","expires":"","registrar":null,"sectors":"General,Mathematics"},{"domain":"sixteen.beauty","status":"available","attractiveness":88,"demand":11,"length":7,"created":"","expires":"","registrar":null,"sectors":"Mathematics"},{"domain":"xiv.beauty","status":"available","attractiveness":86,"demand":12,"length":3,"created":"","expires":"","registrar":null,"sectors":"Mathematics"},{"domain":"xix.beauty","status":"available","attractiveness":86,"demand":11,"length":3,"created":"","expires":"","registrar":null,"sectors":"Mathematics"},{"domain":"cipher.beauty","status":"available","attractiveness":86,"demand":29,"length":6,"created":"","expires":"","registrar":null,"sectors":"Mathematics"},{"domain":"fourteen.beauty","status":"available","attractiveness":84,"demand":8,"length":8,"created":"","expires":"","registrar":null,"sectors":"Mathematics"},{"domain":"thousand.beauty","status":"available","attractiveness":84,"demand":8,"length":8,"created":"","expires":"","registrar":null,"sectors":"Mathematics"},{"domain":"twentytwo.beauty","status":"available","attractiveness":84,"demand":11,"length":10,"created":"","expires":"","registrar":null,"sectors":"Mathematics"},{"domain":"twentyone.beauty","status":"available","attractiveness":84,"demand":13,"length":10,"created":"","expires":"","registrar":null,"sectors":"Mathematics"},{"domain":"nineteen.beauty","status":"available","attractiveness":84,"demand":8,"length":8,"created":"","expires":"","registrar":null,"sectors":"Mathematics"},{"domain":"grand.beauty","status":"expiring","attractiveness":84,"demand":25,"length":5,"created":"2023-08-17T12:11:03.000Z","expires":"2025-08-17T23:59:59.000Z","registrar":"Dynadot LLC","sectors":"Finance,General"},{"domain":"thirteen.beauty","status":"available","attractiveness":84,"demand":10,"length":8,"created":"","expires":"","registrar":null,"sectors":"Mathematics"},{"domain":"dozen.beauty","status":"available","attractiveness":82,"demand":10,"length":5,"created":"","expires":"","registrar":null,"sectors":"Mathematics"},{"domain":"two.beauty","status":"available","attractiveness":80,"demand":24,"length":3,"created":"","expires":"","registrar":null,"sectors":"Mathematics"},{"domain":"first.beauty","status":"available","attractiveness":80,"demand":36,"length":5,"created":"","expires":"","registrar":null,"sectors":"General,Mathematics"},{"domain":"twenty.beauty","status":"available","attractiveness":80,"demand":12,"length":6,"created":"","expires":"","registrar":null,"sectors":"Mathematics"},{"domain":"twentysix.beauty","status":"available","attractiveness":78,"demand":8,"length":10,"created":"","expires":"","registrar":null,"sectors":"Mathematics"},{"domain":"fifteenth.beauty","status":"available","attractiveness":76,"demand":2,"length":9,"created":"","expires":"","registrar":null,"sectors":"Mathematics"},{"domain":"fourteenth.beauty","status":"available","attractiveness":76,"demand":1,"length":10,"created":"","expires":"","registrar":null,"sectors":"Mathematics"},{"domain":"threed.beauty","status":"available","attractiveness":76,"demand":7,"length":7,"created":"","expires":"","registrar":null,"sectors":"Technology"},{"domain":"eighteen.beauty","status":"available","attractiveness":76,"demand":7,"length":8,"created":"","expires":"","registrar":null,"sectors":"Mathematics"},{"domain":"thirteenth.beauty","status":"available","attractiveness":76,"demand":4,"length":10,"created":"","expires":"","registrar":null,"sectors":"Mathematics"},{"domain":"thousandth.beauty","status":"available","attractiveness":76,"demand":1,"length":10,"created":"","expires":"","registrar":null,"sectors":"Mathematics"},{"domain":"nineteenth.beauty","status":"available","attractiveness":76,"demand":3,"length":10,"created":"","expires":"","registrar":null,"sectors":"Mathematics"},{"domain":"hundredth.beauty","status":"available","attractiveness":76,"demand":1,"length":9,"created":"","expires":"","registrar":null,"sectors":"Mathematics"},{"domain":"single.beauty","status":"available","attractiveness":74,"demand":19,"length":6,"created":"","expires":"","registrar":null,"sectors":"Sports"},{"domain":"trinity.beauty","status":"available","attractiveness":72,"demand":18,"length":7,"created":"","expires":"","registrar":null,"sectors":"Religion"},{"domain":"ternary.beauty","status":"available","attractiveness":72,"demand":7,"length":7,"created":"","expires":"","registrar":null,"sectors":"Mathematics"},{"domain":"trey.beauty","status":"available","attractiveness":72,"demand":14,"length":4,"created":"","expires":"","registrar":null,"sectors":"Sports"},{"domain":"unity.beauty","status":"resell","attractiveness":70,"demand":40,"length":5,"created":"2025-02-20T10:27:28.000Z","expires":"2026-02-20T23:59:59.000Z","registrar":"Dynadot LLC","sectors":"Mathematics"},{"domain":"threesome.beauty","status":"available","attractiveness":68,"demand":5,"length":9,"created":"","expires":"","registrar":null,"sectors":"Entertainment"},{"domain":"thirtieth.beauty","status":"available","attractiveness":68,"demand":1,"length":9,"created":"","expires":"","registrar":null,"sectors":"Mathematics"},{"domain":"ane.beauty","status":"available","attractiveness":68,"demand":12,"length":3,"created":"","expires":"","registrar":null,"sectors":"Mathematics"},{"domain":"xvii.beauty","status":"available","attractiveness":66,"demand":5,"length":4,"created":"","expires":"","registrar":null,"sectors":"Mathematics"},{"domain":"xxvi.beauty","status":"available","attractiveness":66,"demand":3,"length":4,"created":"","expires":"","registrar":null,"sectors":"Mathematics"},{"domain":"onec.beauty","status":"available","attractiveness":66,"demand":6,"length":5,"created":"","expires":"","registrar":null,"sectors":"Mathematics"},{"domain":"xxii.beauty","status":"available","attractiveness":66,"demand":6,"length":4,"created":"","expires":"","registrar":null,"sectors":"Mathematics"},{"domain":"xviii.beauty","status":"available","attractiveness":66,"demand":5,"length":5,"created":"","expires":"","registrar":null,"sectors":"Mathematics"},{"domain":"thirty.beauty","status":"available","attractiveness":66,"demand":8,"length":6,"created":"","expires":"","registrar":null,"sectors":"Mathematics"},{"domain":"xxi.beauty","status":"available","attractiveness":66,"demand":10,"length":3,"created":"","expires":"","registrar":null,"sectors":"Mathematics"},{"domain":"xiii.beauty","status":"available","attractiveness":66,"demand":9,"length":4,"created":"","expires":"","registrar":null,"sectors":"Mathematics"},{"domain":"deuce.beauty","status":"available","attractiveness":66,"demand":9,"length":5,"created":"","expires":"","registrar":null,"sectors":"Sports"},{"domain":"tenner.beauty","status":"available","attractiveness":66,"demand":5,"length":6,"created":"","expires":"","registrar":null,"sectors":"Finance"},{"domain":"xii.beauty","status":"available","attractiveness":66,"demand":10,"length":3,"created":"","expires":"","registrar":null,"sectors":"Mathematics"},{"domain":"xxv.beauty","status":"available","attractiveness":66,"demand":6,"length":3,"created":"","expires":"","registrar":null,"sectors":"Mathematics"},{"domain":"century.beauty","status":"available","attractiveness":66,"demand":17,"length":7,"created":"","expires":"","registrar":null,"sectors":"Education"},{"domain":"xvi.beauty","status":"available","attractiveness":66,"demand":5,"length":3,"created":"","expires":"","registrar":null,"sectors":"Mathematics"},{"domain":"clv.beauty","status":"available","attractiveness":66,"demand":10,"length":3,"created":"","expires":"","registrar":null,"sectors":"Mathematics"},{"domain":"longdozen.beauty","status":"available","attractiveness":62,"demand":2,"length":10,"created":"","expires":"","registrar":null,"sectors":"Mathematics"},{"domain":"sixteenth.beauty","status":"available","attractiveness":62,"demand":1,"length":9,"created":"","expires":"","registrar":null,"sectors":"Mathematics"},{"domain":"troika.beauty","status":"available","attractiveness":62,"demand":8,"length":6,"created":"","expires":"","registrar":null,"sectors":"Politics"},{"domain":"twodozen.beauty","status":"available","attractiveness":62,"demand":1,"length":9,"created":"","expires":"","registrar":null,"sectors":"Mathematics"},{"domain":"eighteenth.beauty","status":"available","attractiveness":62,"demand":1,"length":10,"created":"","expires":"","registrar":null,"sectors":"Mathematics"},{"domain":"chiliad.beauty","status":"available","attractiveness":62,"demand":2,"length":7,"created":"","expires":"","registrar":null,"sectors":"Mathematics"},{"domain":"thou.beauty","status":"available","attractiveness":60,"demand":7,"length":4,"created":"","expires":"","registrar":null,"sectors":"Mathematics"},{"domain":"clxxx.beauty","status":"available","attractiveness":60,"demand":1,"length":5,"created":"","expires":"","registrar":null,"sectors":"Mathematics"},{"domain":"cxlv.beauty","status":"available","attractiveness":60,"demand":2,"length":4,"created":"","expires":"","registrar":null,"sectors":"Mathematics"},{"domain":"clxv.beauty","status":"available","attractiveness":60,"demand":1,"length":4,"created":"","expires":"","registrar":null,"sectors":"Mathematics"},{"domain":"cxx.beauty","status":"available","attractiveness":60,"demand":10,"length":3,"created":"","expires":"","registrar":null,"sectors":"Mathematics"},{"domain":"cxxv.beauty","status":"available","attractiveness":60,"demand":1,"length":4,"created":"","expires":"","registrar":null,"sectors":"Mathematics"},{"domain":"clxx.beauty","status":"available","attractiveness":60,"demand":3,"length":4,"created":"","expires":"","registrar":null,"sectors":"Mathematics"},{"domain":"cxxx.beauty","status":"available","attractiveness":60,"demand":4,"length":4,"created":"","expires":"","registrar":null,"sectors":"Mathematics"},{"domain":"clx.beauty","status":"available","attractiveness":60,"demand":10,"length":3,"created":"","expires":"","registrar":null,"sectors":"Mathematics"},{"domain":"cxv.beauty","status":"available","attractiveness":60,"demand":4,"length":3,"created":"","expires":"","registrar":null,"sectors":"Mathematics"},{"domain":"cxxxv.beauty","status":"available","attractiveness":60,"demand":2,"length":5,"created":"","expires":"","registrar":null,"sectors":"Mathematics"},{"domain":"clxxv.beauty","status":"available","attractiveness":60,"demand":1,"length":5,"created":"","expires":"","registrar":null,"sectors":"Mathematics"},{"domain":"cxl.beauty","status":"available","attractiveness":60,"demand":7,"length":3,"created":"","expires":"","registrar":null,"sectors":"Mathematics"},{"domain":"xcl.beauty","status":"available","attractiveness":60,"demand":5,"length":3,"created":"","expires":"","registrar":null,"sectors":"Mathematics"},{"domain":"centesimal.beauty","status":"available","attractiveness":58,"demand":1,"length":10,"created":"","expires":"","registrar":null,"sectors":"Mathematics"},{"domain":"twelfth.beauty","status":"available","attractiveness":58,"demand":2,"length":7,"created":"","expires":"","registrar":null,"sectors":"Mathematics"},{"domain":"cypher.beauty","status":"available","attractiveness":58,"demand":29,"length":6,"created":"","expires":"","registrar":null,"sectors":"Mathematics"},{"domain":"xxviii.beauty","status":"available","attractiveness":56,"demand":1,"length":6,"created":"","expires":"","registrar":null,"sectors":"Mathematics"},{"domain":"thirtyone.beauty","status":"available","attractiveness":56,"demand":5,"length":10,"created":"","expires":"","registrar":null,"sectors":"Mathematics"},{"domain":"xxiii.beauty","status":"available","attractiveness":56,"demand":5,"length":5,"created":"","expires":"","registrar":null,"sectors":"Mathematics"},{"domain":"xxix.beauty","status":"available","attractiveness":56,"demand":4,"length":4,"created":"","expires":"","registrar":null,"sectors":"Mathematics"},{"domain":"xxxi.beauty","status":"available","attractiveness":56,"demand":9,"length":4,"created":"","expires":"","registrar":null,"sectors":"Mathematics"},{"domain":"xxvii.beauty","status":"available","attractiveness":56,"demand":3,"length":5,"created":"","expires":"","registrar":null,"sectors":"Mathematics"},{"domain":"thirtytwo.beauty","status":"available","attractiveness":56,"demand":5,"length":10,"created":"","expires":"","registrar":null,"sectors":"Mathematics"},{"domain":"xxiv.beauty","status":"available","attractiveness":56,"demand":5,"length":4,"created":"","expires":"","registrar":null,"sectors":"Mathematics"},{"domain":"deuceace.beauty","status":"available","attractiveness":54,"demand":2,"length":9,"created":"","expires":"","registrar":null,"sectors":"Sports"},{"domain":"triplet.beauty","status":"available","attractiveness":50,"demand":8,"length":7,"created":"","expires":"","registrar":null,"sectors":"Science"}]